blnconverter/__init__.py
blnconverter/__main__.py
blnconverter/src/__init__.py
blnconverter/src/blnconverter.py
bln_converter-1.0.2.dist-info/LICENSE
bln_converter-1.0.2.dist-info/METADATA
bln_converter-1.0.2.dist-info/WHEEL
bln_converter-1.0.2.dist-info/entry_points.txt
bln_converter-1.0.2.dist-info/top_level.txt
bln_converter-1.0.2.dist-info/RECORD
