Metadata-Version: 2.1
Name: bln-converter
Version: 1.0.2
Summary: Easy BLN file conversion to ESRI shape or GeoJSON
Home-page: https://github.com/ericmiguel/bln-converter
Author: Eric Miguel Ribeiro
Author-email: ericmiguel@id.uff.br
License: UNKNOWN
Platform: UNKNOWN
Classifier: Programming Language :: Python :: 3
Classifier: License :: OSI Approved :: MIT License
Classifier: Operating System :: OS Independent
Requires-Python: >=3.7
Requires-Dist: certifi (==2020.12.5)
Requires-Dist: click (==7.1.2)
Requires-Dist: click-plugins (==1.1.1)
Requires-Dist: cligj (==0.7.1)
Requires-Dist: fiona (==1.8.18)
Requires-Dist: geopandas (==0.8.1)
Requires-Dist: munch (==2.5.0)
Requires-Dist: numpy (==1.19.5)
Requires-Dist: pandas (==1.2.0)
Requires-Dist: pycodestyle (==2.6.0)
Requires-Dist: pyproj (==3.0.0.post1)
Requires-Dist: python-dateutil (==2.8.1)
Requires-Dist: pytz (==2020.5)
Requires-Dist: Shapely (==1.7.1)
Requires-Dist: six (==1.15.0)
Requires-Dist: toml (==0.10.2)
